Workbook

Sheet ВОР 150200 КЖ5
G1: Приложение № 2.2
F2: к Техническому заданию №___________________
G4: УТВЕРЖДАЮ
E5: Директор департамента по строительству
E6: ООО "ОК РУСАЛ Промтехразвитие"
G8: (Ф.И.О)
F9: " "
C13: ВОР № ______ от _17.06.2025г._
B14: (взамен ВОР № ______ от ________________ по причине___
B15: (доп. к ВОР № ______ от ________________ по причине___)
A17: Код ИСР, СПП-элемент, объект: | D17: 150200 Отделение переработки электролита (ОПЭ)
A18: Основание (проект): | D18: 440.02723.150200.1.6-КЖ5 (изм.0)
A20: Наименование работ: | D20: Пристройки. Ростверки, фундаменты и фундаментные балки
A23: № п/п | B23: Наименование работ и затрат | C23: Ед. изм. | D23: Кол-во | E23: Формула расчета объемов работ и расхода материалов, потребности ресурсов | F23: Ссылка на чертежи, спецификации в проектной документации | G23: Примечание
A24: 1 | B24: 2 | C24: 3 | D24: 4 | E24: 5 | F24: 6 | G24: 7
A25: Раздел 1. Земляные работы
A26: 1 | B26: Устройство основания под фундаменты: щебеночного | C26: м3 | D26: =((2.2*2.9)+(3.9*2.6)+(3.4*4.3)+(4.5*3.6)+(3.3*1.9)+(3.3*1.9))*0.8 -> 47.904 | E26: ((2,2*2,9)+(3,9*2,6)+(3,4*4,3)+(4,5*3,6)+(3,3*1,9)+(3,3*1,9))*0,8 | I26: расход 1,15 для основания
B27: Щебень фр. 20-40 (k упл.>0,97) | C27: м3 | D27: =47.9*1.15-8.262 -> 46.823 | E27: 47,9*1,15-8,262 | G27: k=1,15 | H27: 45,97м3 | I27: 47,9*1,15-9,12
B28: Щебень фр. 5-10 (на расклинцовку) | C28: м3 | D28: =55.085*0.15 -> 8.26275 | E28: 55,085*0,15 | G28: k=0,15 | H28: 9,12м3
A29: Раздел 2. Ростверки
A30: Ростверк Рсм1 - 13 шт.
A31: =A26+1 -> 2 | B31: Устройство бетонной подготовки | C31: м3 | D31: =0.14*13 -> 1.82 | E31: 0,14*13 | F31: 440.02723.150200.1.6-КЖ5, лист 7
B32: Бетон В7,5 | C32: м3 | D32: =0.14*13*1.02 -> 1.8564 | E32: 0,14*13*1,02 | G32: ГОСТ 26633-2015 | I32: расход В7,5 1,02
A33: =A31+1 -> 3 | B33: Устройство железобетонных фундаментов общего назначения под колонны объемом: до 3 м3 | C33: м3 | D33: =0.8*13 -> 10.4 | E33: 0,8*13
B34: Бетон В25 F150 W6 | C34: м3 | D34: =0.8*13*1.015 -> 10.556 | E34: 0,8*13*1,015 | G34: ГОСТ 26633-2015 | I34: расход В25 1,015
B35: Арматура Ø16 А500С (арматурные заготовки/детали) | C35: т | D35: =(4*3.82+4*2.56)*13/1000 -> 0.33176 | E35: (4*3,82+4*2,56)*13/1000 | G35: ГОСТ 34028-2016
B36: Арматура Ø14А500С (арматурные заготовки/детали) | C36: т | D36: =(14*1.72+14*2.88)*13/1000 -> 0.8372 | E36: (14*1,72+14*2,88)*13/1000 | G36: ГОСТ 34028-2016
B37: Арматура Ø8 А240 | C37: т | D37: =12*0.37*13/1000 -> 0.05772 | E37: 12*0,37*13/1000 | G37: ГОСТ 5781-82
B38: Арматура Ø8 А240 (арматурные заготовки/детали) | C38: т | D38: =(2*0.54+4*0.19)*13/1000 -> 0.02392 | E38: (2*0,54+4*0,19)*13/1000 | G38: ГОСТ 5781-82
A39: Ростверк Рсм2 - 1 шт.
A40: =A33+1 -> 4 | B40: Устройство бетонной подготовки | C40: м3 | D40: =0.3 -> 0.3 | E40: 0.3 | F40: 440.02723.150200.1.6-КЖ5, лист 7
B41: Бетон В7,5 | C41: м3 | D41: =0.3*1.02 -> 0.306 | E41: 0,3*1,02 | G41: ГОСТ 26633-2015
A42: =A40+1 -> 5 | B42: Устройство железобетонных фундаментов общего назначения под колонны объемом: до 3 м3 | C42: м3 | D42: =2.22 -> 2.22 | E42: 2.22
B43: Бетон В25 F150 W6 | C43: м3 | D43: =2.22*1.015 -> 2.2533 | E43: 2,22*1,015 | G43: ГОСТ 26633-2015
B44: Арматура Ø20 А500С (арматурные заготовки/детали) | C44: т | D44: =14*6.71/1000 -> 0.09394 | E44: 14*6,71/1000 | G44: ГОСТ 34028-2016
B45: Арматура Ø16 А500С | C45: т | D45: =6*3.55/1000 -> 0.0213 | E45: 6*3,55/1000 | G45: ГОСТ 34028-2016
B46: Арматура Ø16 А500С (арматурные заготовки/детали) | C46: т | D46: =(6*4.91+6*5.34)/1000 -> 0.0615 | E46: (6*4,91+6*5,34)/1000 | G46: ГОСТ 34028-2016
B47: Арматура Ø12 А500С (арматурные заготовки/детали) | C47: т | D47: =4*1.62/1000 -> 0.00648 | E47: 4*1,62/1000 | G47: ГОСТ 34028-2016
B48: Арматура Ø10 А240 (арматурные заготовки/детали) | C48: т | D48: =(12*1.98+24*1.09+36*0.64)/1000 -> 0.07296 | E48: (12*1,98+24*1,09+36*0,64)/1000 | G48: ГОСТ 5781-82
B49: Арматура Ø8 А240 (арматурные заготовки/детали) | C49: т | D49: =(2*0.39)/1000 -> 0.00078 | E49: (2*0,39)/1000 | G49: ГОСТ 5781-82
A50: Раздел 3. Фундаменты
A51: Фундамент ФОм1 - 1 шт.
A52: =A42+1 -> 6 | B52: Устройство бетонной подготовки | C52: м3 | D52: =0.64 -> 0.64 | E52: =0.64 -> 0.64 | F52: 440.02723.150200.1.6-КЖ5, лист 8
B53: Бетон В7,5 | C53: м3 | D53: =0.64*1.02 -> 0.6528 | E53: 0,64*1,02 | G53: ГОСТ 26633-2015
A54: =A52+1 -> 7 | B54: Устройство железобетонных фундаментов общего назначения объемом: до 25 м3 | C54: м3 | D54: =5.94 -> 5.94 | E54: =5.94 -> 5.94
B55: Бетон В25 F150 W6 | C55: м3 | D55: =5.94*1.015 -> 6.0291 | E55: 5,94*1,015 | G55: ГОСТ 26633-2015
B56: Арматура Ø12 А500С | C56: т | D56: =30*2.35/1000 -> 0.0705 | E56: 30*2,35/1000 | G56: ГОСТ 34028-2016
B57: Арматура Ø12 А500С (арматурные заготовки/детали) | C57: т | D57: =28*2.75/1000 -> 0.077 | E57: 28*2,75/1000 | G57: ГОСТ 34028-2016
A58: 6.1 | B58: Каркас пространственный КП4 - 2 шт. (с учетом изготовления), Каркас Кр1 - 2шт., Арматура Ø12-А500С ГОСТ 34028-2016 | C58: т | D58: =35.5*2/1000 -> 0.071 | E58: 35,5*2/1000 | F58: 440.02723.150200.1.6-КЖ5, лист 17
B59: (КП4) Арматура Ø12 А500С | C59: т | D59: =35.5*2/1000 -> 0.071 | E59: 35,5*2/1000 | G59: ГОСТ 34028-2016
A60: Фундамент ФОм2 - 1 шт.
A61: =A54+1 -> 8 | B61: Устройство бетонной подготовки | C61: м3 | D61: 1.01 | E61: 1.01 | F61: 440.02723.150200.1.6-КЖ5, лист 8
B62: Бетон В7,5 | C62: м3 | D62: =1.01*1.02 -> 1.0302 | E62: 1,01*1,02 | G62: ГОСТ 26633-2015
A63: =A61+1 -> 9 | B63: Устройство железобетонных фундаментов общего назначения объемом: до 25 м3 | C63: м3 | D63: 9.77 | E63: 9.77
B64: Бетон В25 F150 W6 | C64: м3 | D64: =9.77*1.015 -> 9.91655 | E64: 9,77*1,015 | G64: ГОСТ 26633-2015
B65: Арматура Ø12 А500С | C65: т | D65: =34*3.24/1000 -> 0.11016 | E65: 34*3,24/1000 | G65: ГОСТ 34028-2016
B66: Арматура Ø12 А500С (арматурные заготовки/детали) | C66: т | D66: =38*3.11/1000 -> 0.11818 | E66: 38*3,11/1000 | G66: ГОСТ 34028-2016
A67: 8.1 | B67: Каркас пространственный КП5 - 3 шт. (с учетом изготовления), Каркас Кр2 - 2шт., Арматура Ø12-А500С ГОСТ 34028-2016 | C67: т | D67: =3*41.83/1000 -> 0.12549 | E67: 3*41,83/1000 | F67: 440.02723.150200.1.6-КЖ5, лист 17
B68: (КП5) Арматура Ø12 А500С | C68: т | D68: =3*41.83/1000 -> 0.12549 | E68: 3*41,83/1000 | G68: ГОСТ 34028-2016
A69: Фундамент ФОм3 - 1 шт.
A70: =A63+1 -> 10 | B70: Устройство бетонной подготовки | C70: м3 | D70: =1.46 -> 1.46 | E70: =1.46 -> 1.46 | F70: 440.02723.150200.1.6-КЖ5, лист 9
B71: Бетон В7,5 | C71: м3 | D71: =1.46*1.02 -> 1.4892 | E71: 1,46*1,02 | G71: ГОСТ 26633-2015
A72: =A70+1 -> 11 | B72: Устройство железобетонных фундаментов общего назначения объемом: до 25 м3 | C72: м3 | D72: =11.64 -> 11.64 | E72: =11.64 -> 11.64
B73: Бетон В25 F150 W6 | C73: м3 | D73: =11.64*1.015 -> 11.8146 | E73: 11,64*1,015 | G73: ГОСТ 26633-2015
B74: Арматура Ø16 А500С (арматурные заготовки/детали) | C74: т | D74: =32*1.97/1000 -> 0.06304 | E74: 32*1,97/1000 | G74: ГОСТ 34028-2016
B75: Арматура Ø14 А500С | C75: т | D75: =(22*4.89+28*3.81)/1000 -> 0.21426 | E75: (22*4,89+28*3,81)/1000 | G75: ГОСТ 34028-2016
B76: Арматура Ø14 А500С (арматурные заготовки/детали) | C76: т | D76: =(28*2.62+22*2.57)/1000 -> 0.1299 | E76: (28*2,62+22*2,57)/1000 | G76: ГОСТ 34028-2016
B77: Арматура Ø8 А240 (арматурные заготовки/детали) | C77: т | D77: =16*0.56/1000 -> 0.00896 | E77: 16*0,56/1000 | G77: ГОСТ 5781-82
A78: 10.1 | B78: Каркас пространственный КП6 - 3 шт. (с учетом изготовления), Каркас Кр3 - 2шт., Арматура Ø12-А500С ГОСТ 34028-2016 | C78: т | D78: =3*48.48/1000 -> 0.14544 | E78: 3*48,48/1000 | F78: 440.02723.150200.1.6-КЖ5, лист 17
B79: (КП6) Арматура Ø12 А500С | C79: т | D79: =3*48.48/1000 -> 0.14544 | E79: 3*48,48/1000 | G79: ГОСТ 34028-2016
A80: =A72+1 -> 12 | B80: Установка закладных деталей весом: свыше 4 до 20 кг | C80: т | D80: =(386.6+4*10.17)/1000 -> 0.42728 | E80: (386,6+4*10,17)/1000
A81: 11.1 | B81: Закладное изделие Зд1 с АКЗ - 1 шт. | C81: т | D81: =386.6/1000 -> 0.3866 | E81: 386,6/1000 | F81: 440.02723.150200.1.6-КЖ5, лист 18
B82: (Зд1) Болт 1.1 М20х600, сталь 09Г2С-6 | C82: т | D82: =20*1.81/1000 -> 0.0362 | E82: 20*1,81/1000 | G82: ГОСТ 24379.1-2012
B83: (Зд1) Лист 20х1450, сталь С245 | C83: т | D83: =330.09/1000 -> 0.33009 | E83: 330,09/1000 | G83: ГОСТ19903-2015
B84: (Зд1) Арматура Ø14 А500С | C84: т | D84: =48*0.42/1000 -> 0.02016 | E84: 48*0,42/1000 | G84: ГОСТ 34028-2016
A85: 11.2 | B85: Закладное изделие Зд3 с АКЗ - 4 шт. | C85: т | D85: =4*10.17/1000 -> 0.04068 | E85: 4*10,17/1000 | F85: 440.02723.150200.1.6-КЖ5, лист 18
B86: (Зд1) Лист 12х300х300, сталь С245 | C86: т | D86: =8.48*4/1000 -> 0.03392 | E86: 8,48*4/1000 | G86: ГОСТ19903-2015
B87: (Зд1) Арматура Ø14 А500С, L=350 мм | C87: т | D87: =4*0.42*4/1000 -> 0.00672 | E87: 4*0,42*4/1000 | G87: ГОСТ 34028-2016
A88: Фундамент ФОм4 - 1 шт.
A89: =A80+1 -> 13 | B89: Устройство бетонной подготовки | C89: м3 | D89: =1.62 -> 1.62 | E89: 1.62 | F89: 440.02723.150200.1.6-КЖ5, лист 9
B90: Бетон В7,5 | C90: м3 | D90: =1.62*1.02 -> 1.6524 | E90: 1,62*1,02 | G90: ГОСТ 26633-2015
A91: =A89+1 -> 14 | B91: Устройство железобетонных фундаментов общего назначения объемом: до 25 м3 | C91: м3 | D91: =13.12 -> 13.12 | E91: 13.12
B92: Бетон В25 F150 W6 | C92: м3 | D92: =13.12*1.015 -> 13.3168 | E92: 13,12*1,015 | G92: ГОСТ 26633-2015
B93: Арматура Ø16 А500С (арматурные заготовки/детали) | C93: т | D93: =32*1.97/1000 -> 0.06304 | E93: 32*1,97/1000 | G93: ГОСТ 34028-2016
B94: Арматура Ø14 А500С | C94: т | D94: =(23*5.14+29*4.05)/1000 -> 0.23567 | E94: (23*5,14+29*4,05)/1000 | G94: ГОСТ 34028-2016
B95: Арматура Ø14 А500С (арматурные заготовки/детали) | C95: т | D95: =(29*2.62+23*2.57)/1000 -> 0.13509 | E95: (29*2,62+23*2,57)/1000 | G95: ГОСТ 34028-2016
B96: Арматура Ø8 А240 (арматурные заготовки/детали) | C96: т | D96: =16*0.56/1000 -> 0.00896 | E96: 16*0,56/1000 | G96: ГОСТ 5781-82
A97: 13.1 | B97: Каркас пространственный КП6 - 3шт. (с учетом изготовления), Каркас Кр3 - 2шт., Арматура Ø12-А500С ГОСТ 34028-2016 | C97: т | D97: =3*48.48/1000 -> 0.14544 | E97: 3*48,48/1000 | F97: 440.02723.150200.1.6-КЖ5, лист 17
B98: (КП6) Арматура Ø12 А500С | C98: т | D98: =3*48.48/1000 -> 0.14544 | E98: 3*48,48/1000 | G98: ГОСТ 34028-2016
A99: =A91+1 -> 15 | B99: Установка закладных деталей весом: свыше 4 до 20 кг | C99: т | D99: =(347.13+4*10.17)/1000 -> 0.38781 | E99: (347,13+4*10,17)/1000
A100: 14.1 | B100: Закладное изделие Зд2 с АКЗ - 1 шт. | C100: т | D100: =347.13/1000 -> 0.34713 | E100: 347,13/1000 | F100: 440.02723.150200.1.6-КЖ5, лист 18
B101: (Зд1) Болт 1.1 М20х600, сталь 09Г2С-6 | C101: т | D101: =24*1.81/1000 -> 0.04344 | E101: 24*1,81/1000 | G101: ГОСТ 24379.1-2012
B102: (Зд1) Лист 10х1900х1900 сталь С245 | C102: т | D102: =283.39/1000 -> 0.28339 | E102: 283,39/1000 | G102: ГОСТ19903-2015
B103: (Зд1) Арматура Ø14 А500С | C103: т | D103: =48*0.42/1000 -> 0.02016 | E103: 48*0,42/1000 | G103: ГОСТ 34028-2016
A104: 14.2 | B104: Закладное изделие Зд3 с АКЗ - 4 шт. | C104: т | D104: =4*10.17/1000 -> 0.04068 | E104: 4*10,17/1000 | F104: 440.02723.150200.1.6-КЖ5, лист 18
B105: (Зд1) Лист 12х300х300, сталь С245 | C105: т | D105: =8.48*4/1000 -> 0.03392 | E105: 8,48*4/1000 | G105: ГОСТ19903-2015
B106: (Зд1) Арматура Ø14 А500С, L=350 мм | C106: т | D106: =4*0.42*4/1000 -> 0.00672 | E106: 4*0,42*4/1000 | G106: ГОСТ 34028-2016
A107: Фундамент ФОм5, ФОм5а - 2 шт.
A108: =A99+1 -> 16 | B108: Устройство бетонной подготовки | C108: м3 | D108: =0.63*2 -> 1.26 | E108: =0.63*2 -> 1.26 | F108: 440.02723.150200.1.6-КЖ5, лист 10
B109: Бетон В7,5 | C109: м3 | D109: =0.63*2*1.02 -> 1.2852 | E109: 0,63*2*1,02 | G109: ГОСТ 26633-2015
...

Sheet ПСЦМ 150200 КЖ5
K1: Приложение №3.2 к Техническому заданию №___________________
A2: Протокол согласования цен на материалы №___ от
A3: на устройство ростверков, фундаментов и фундаментных балок пристроек к здянию отделения переработки электролита (ОПЭ) в рамках реализации проекта «Братский алюминиевый завод. Экологическая реконструкция»
C4: (440.02723.150200.1.6-КЖ5 (изм.0))
A6: № п/п | B6: Населенный пункт и регион | C6: Наименование и техническая характеристика оборудования и материалов | D6: Тип, марка, ГОСТ | E6: Код оборудования (артикул) оборудования, изделия, материала | F6: Ед. изм. | G6: Кол-во | H6: Цена подрядной организации ( с учетом доставки), руб без НДС | I6: Сумма подрядной организации ( с учетом доставки), руб без НДС | J6: Цена коммерческого обзора (с учетом доставки), руб без НДС | K6: Сумма коммерческого обзора (с учетом доставки), руб без НДС | L6: Цена согласованная в смету (с учетом доставки), руб без НДС | M6: Сумма согласованная в смету (с учетом доставки), руб без НДС | N6: Примечание (Источник цены коммерческого обзора: КП, № счета, ссылка на интернет-магазин, прайс категорийной стратегии, конкурентный отбор и пр.)
A7: 2 | B7: 2 | C7: 3 | D7: 4 | E7: 5 | F7: 6 | G7: 7 | H7: 8 | I7: 9 | J7: 10 | K7: 11 | L7: 12 | M7: 13 | N7: 14
A8: 1 | B8: г. Братск Иркутской области | C8: Щебень фр. 20-40 | D8: ГОСТ 8267-93 | F8: м3 | G8: ='ВОР 150200 КЖ5'!D27 -> 46.823
A9: =A8+1 -> 2 | B9: г. Братск Иркутской области | C9: Щебень фр. 5-10 | D9: ГОСТ 8267-93 | F9: м3 | G9: ='ВОР 150200 КЖ5'!D28 -> 8.26275
A10: =A9+1 -> 3 | B10: г. Братск Иркутской области | C10: Бетон В7,5 | D10: ГОСТ 26633-2015 | F10: м3 | G10: ='ВОР 150200 КЖ5'!D32+'ВОР 150200 КЖ5'!D41+'ВОР 150200 КЖ5'!D53+'ВОР 150200 КЖ5'!D62+'ВОР 150200 КЖ5'!D71+'ВОР 150200 КЖ5'!D90+'ВОР 150200 КЖ5'!D109+'ВОР 150200 КЖ5'!D135+'ВОР 150200 КЖ5'!D144+'ВОР 150200 КЖ5'!D153+'ВОР 150200 КЖ5'!D163+'ВОР 150200 КЖ5'!D173+'ВОР 150200 КЖ5'!D186+'ВОР 150200 КЖ5'!D199+'ВОР 150200 КЖ5'!D209+'ВОР 150200 КЖ5'!D219+'ВОР 150200 КЖ5'!D229+'ВОР 150200 КЖ5'!D237+'ВОР 150200 КЖ5'!D247+'ВОР 150200 КЖ5'!D256+'ВОР 150200 КЖ5'!D265+'ВОР 150200 КЖ5'!D273+'ВОР 150200 КЖ5'!D282+'ВОР 150200 КЖ5'!D291 -> 15.3306
A11: =A10+1 -> 4 | B11: г. Братск Иркутской области | C11: Бетон В25 W6 F150 | D11: ГОСТ 26633-2015 | F11: м3 | G11: ='ВОР 150200 КЖ5'!D34+'ВОР 150200 КЖ5'!D43+'ВОР 150200 КЖ5'!D55+'ВОР 150200 КЖ5'!D64+'ВОР 150200 КЖ5'!D73+'ВОР 150200 КЖ5'!D92+'ВОР 150200 КЖ5'!D111+'ВОР 150200 КЖ5'!D137+'ВОР 150200 КЖ5'!D146+'ВОР 150200 КЖ5'!D155+'ВОР 150200 КЖ5'!D165+'ВОР 150200 КЖ5'!D175+'ВОР 150200 КЖ5'!D188+'ВОР 150200 КЖ5'!D201+'ВОР 150200 КЖ5'!D211+'ВОР 150200 КЖ5'!D221+'ВОР 150200 КЖ5'!D231+'ВОР 150200 КЖ5'!D239+'ВОР 150200 КЖ5'!D249+'ВОР 150200 КЖ5'!D258+'ВОР 150200 КЖ5'!D267+'ВОР 150200 КЖ5'!D275+'ВОР 150200 КЖ5'!D284+'ВОР 150200 КЖ5'!D293 -> 139.11695
A12: =A11+1 -> 5 | B12: г. Братск Иркутской области | C12: Арматура ∅20-А500С | D12: ГОСТ34028-2016 | F12: т | G12: ='ВОР 150200 КЖ5'!D176+'ВОР 150200 КЖ5'!D189 -> 0.09594
A13: =A12+1 -> 6 | B13: г. Братск Иркутской области | C13: Арматура ∅20-А500С (арматурные заготовки/детали) | D13: ГОСТ34028-2016 | F13: т | G13: ='ВОР 150200 КЖ5'!D44+'ВОР 150200 КЖ5'!D138+'ВОР 150200 КЖ5'!D147+'ВОР 150200 КЖ5'!D156+'ВОР 150200 КЖ5'!D166+'ВОР 150200 КЖ5'!D202+'ВОР 150200 КЖ5'!D212+'ВОР 150200 КЖ5'!D222+'ВОР 150200 КЖ5'!D240+'ВОР 150200 КЖ5'!D250+'ВОР 150200 КЖ5'!D259 -> 1.11523
A14: =A13+1 -> 7 | B14: г. Братск Иркутской области | C14: Арматура ∅16-А500С | D14: ГОСТ34028-2016 | F14: т | G14: ='ВОР 150200 КЖ5'!D45+'ВОР 150200 КЖ5'!D203 -> 0.0605
A15: =A14+1 -> 8 | B15: г. Братск Иркутской области | C15: Арматура ∅16-А500С (арматурные заготовки/детали) | D15: ГОСТ34028-2016 | F15: т | G15: ='ВОР 150200 КЖ5'!D35+'ВОР 150200 КЖ5'!D46+'ВОР 150200 КЖ5'!D74+'ВОР 150200 КЖ5'!D93+'ВОР 150200 КЖ5'!D157+'ВОР 150200 КЖ5'!D167+'ВОР 150200 КЖ5'!D213+'ВОР 150200 КЖ5'!D223+'ВОР 150200 КЖ5'!D232+'ВОР 150200 КЖ5'!D241+'ВОР 150200 КЖ5'!D268+'ВОР 150200 КЖ5'!D276+'ВОР 150200 КЖ5'!D285+'ВОР 150200 КЖ5'!D294 -> 1.10114
A16: =A15+1 -> 9 | B16: г. Братск Иркутской области | C16: Арматура ∅14-А500С | D16: ГОСТ34028-2016 | F16: т | G16: ='ВОР 150200 КЖ5'!D75+'ВОР 150200 КЖ5'!D94 -> 0.44993
A17: =A16+1 -> 10 | B17: г. Братск Иркутской области | C17: Арматура ∅14-А500С (арматурные заготовки/детали) | D17: ГОСТ34028-2016 | F17: т | G17: ='ВОР 150200 КЖ5'!D36+'ВОР 150200 КЖ5'!D76+'ВОР 150200 КЖ5'!D95 -> 1.10219
A18: =A17+1 -> 11 | B18: г. Братск Иркутской области | C18: Арматура ∅12-А500С | D18: ГОСТ34028-2016 | F18: т | G18: ='ВОР 150200 КЖ5'!D56+'ВОР 150200 КЖ5'!D65+'ВОР 150200 КЖ5'!D139+'ВОР 150200 КЖ5'!D148+'ВОР 150200 КЖ5'!D158+'ВОР 150200 КЖ5'!D168+'ВОР 150200 КЖ5'!D177+'ВОР 150200 КЖ5'!D178+'ВОР 150200 КЖ5'!D182+'ВОР 150200 КЖ5'!D190+'ВОР 150200 КЖ5'!D195+'ВОР 150200 КЖ5'!D204+'ВОР 150200 КЖ5'!D214+'ВОР 150200 КЖ5'!D224+'ВОР 150200 КЖ5'!D233+'ВОР 150200 КЖ5'!D242+'ВОР 150200 КЖ5'!D251+'ВОР 150200 КЖ5'!D260+'ВОР 150200 КЖ5'!D269+'ВОР 150200 КЖ5'!D277+'ВОР 150200 КЖ5'!D286+'ВОР 150200 КЖ5'!D295 -> 4.52352
A19: =A18+1 -> 12 | B19: г. Братск Иркутской области | C19: Арматура ∅12-А500С (арматурные заготовки/детали) | D19: ГОСТ34028-2016 | F19: т | G19: ='ВОР 150200 КЖ5'!D47+'ВОР 150200 КЖ5'!D57+'ВОР 150200 КЖ5'!D66+'ВОР 150200 КЖ5'!D140+'ВОР 150200 КЖ5'!D149+'ВОР 150200 КЖ5'!D159+'ВОР 150200 КЖ5'!D169+'ВОР 150200 КЖ5'!D178+'ВОР 150200 КЖ5'!D191+'ВОР 150200 КЖ5'!D205+'ВОР 150200 КЖ5'!D215+'ВОР 150200 КЖ5'!D225+'ВОР 150200 КЖ5'!D243+'ВОР 150200 КЖ5'!D252+'ВОР 150200 КЖ5'!D261+'ВОР 150200 КЖ5'!D278+'ВОР 150200 КЖ5'!D287+'ВОР 150200 КЖ5'!D296 -> 1.59576
A20: =A19+1 -> 13 | B20: г. Братск Иркутской области | C20: Арматура ∅10-А500С | D20: ГОСТ34028-2016 | F20: т | G20: ='ВОР 150200 КЖ5'!D112 -> 0.13664
A21: =A20+1 -> 14 | B21: г. Братск Иркутской области | C21: Арматура ∅10-А500С (арматурные заготовки/детали) | D21: ГОСТ34028-2016 | F21: т | G21: ='ВОР 150200 КЖ5'!D113 -> 0.16242
A22: =A21+1 -> 15 | B22: г. Братск Иркутской области | C22: Арматура ∅10-А240 (арматурные заготовки/детали) | D22: ГОСТ 5781-82 | F22: т | G22: ='ВОР 150200 КЖ5'!D48 -> 0.07296
A23: =A22+1 -> 16 | B23: г. Братск Иркутской области | C23: Арматура ∅8-А240 | D23: ГОСТ 5781-82 | F23: т | G23: ='ВОР 150200 КЖ5'!D37 -> 0.05772
A24: =A23+1 -> 17 | B24: г. Братск Иркутской области | C24: Арматура ∅8-А240 (арматурные заготовки/детали) | D24: ГОСТ 5781-82 | F24: т | G24: ='ВОР 150200 КЖ5'!D38+'ВОР 150200 КЖ5'!D49+'ВОР 150200 КЖ5'!D77+'ВОР 150200 КЖ5'!D96+'ВОР 150200 КЖ5'!D141+'ВОР 150200 КЖ5'!D150+'ВОР 150200 КЖ5'!D160+'ВОР 150200 КЖ5'!D170+'ВОР 150200 КЖ5'!D179+'ВОР 150200 КЖ5'!D192+'ВОР 150200 КЖ5'!D206+'ВОР 150200 КЖ5'!D216+'ВОР 150200 КЖ5'!D226+'ВОР 150200 КЖ5'!D234+'ВОР 150200 КЖ5'!D244+'ВОР 150200 КЖ5'!D253+'ВОР 150200 КЖ5'!D262+'ВОР 150200 КЖ5'!D270+'ВОР 150200 КЖ5'!D279+'ВОР 150200 КЖ5'!D288+'ВОР 150200 КЖ5'!D297 -> 0.78319
A25: =A24+1 -> 18 | B25: г. Братск Иркутской области | C25: Каркас пространственный КП4 (2 шт.) | D25: 440.02723.150200.1.6-КЖ5, лист 17 | F25: т | G25: ='ВОР 150200 КЖ5'!D58 -> 0.071
A26: =A25+1 -> 19 | B26: г. Братск Иркутской области | C26: Каркас пространственный КП5 (3 шт.) | D26: 440.02723.150200.1.6-КЖ5, лист 17 | F26: т | G26: ='ВОР 150200 КЖ5'!D68 -> 0.12549
A27: =A26+1 -> 20 | B27: г. Братск Иркутской области | C27: Каркас пространственный КП6 (6 шт.) | D27: 440.02723.150200.1.6-КЖ5, лист 17 | F27: т | G27: ='ВОР 150200 КЖ5'!D78+'ВОР 150200 КЖ5'!D97 -> 0.29088
A28: =A27+1 -> 21 | B28: г. Братск Иркутской области | C28: Изделие закладное ЗД1 с АКЗ (1 шт.) | D28: 440.02723.150200.1.6-КЖ5, лист 18 | F28: т | G28: ='ВОР 150200 КЖ5'!D81 -> 0.3866
A29: =A28+1 -> 22 | B29: г. Братск Иркутской области | C29: Изделие закладное ЗД2 с АКЗ (1 шт.) | D29: 440.02723.150200.1.6-КЖ5, лист 18 | F29: т | G29: ='ВОР 150200 КЖ5'!D100 -> 0.34713
A30: =A29+1 -> 23 | B30: г. Братск Иркутской области | C30: Изделие закладное ЗД3 с АКЗ (8 шт.) | D30: 440.02723.150200.1.6-КЖ5, лист 18 | F30: т | G30: ='ВОР 150200 КЖ5'!D85+'ВОР 150200 КЖ5'!D104 -> 0.08136
A31: =A30+1 -> 24 | B31: г. Братск Иркутской области | C31: Изделие закладное ЗД4 с АКЗ (4 шт.) | D31: 440.02723.150200.1.6-КЖ5, лист 19 | F31: т | G31: ='ВОР 150200 КЖ5'!D115 -> 0.05956
A32: =A31+1 -> 25 | B32: г. Братск Иркутской области | C32: Изделие закладное ЗД5 с АКЗ (4 шт.) | D32: 440.02723.150200.1.6-КЖ5, лист 19 | F32: т | G32: ='ВОР 150200 КЖ5'!D118 -> 0.03524
A33: =A32+1 -> 26 | B33: г. Братск Иркутской области | C33: Изделие закладное ЗД6 с АКЗ (4 шт.) | D33: 440.02723.150200.1.6-КЖ5, лист 19 | F33: т | G33: ='ВОР 150200 КЖ5'!D121 -> 0.03268
A34: =A33+1 -> 27 | B34: г. Братск Иркутской области | C34: Экструдированный пенополистирол (XPS) толщина 100 мм | D34: 440.02723.150200.1.6-КЖ5, лист 4, п.7 | F34: м3 | G34: ='ВОР 150200 КЖ5'!D125 -> 0.03
A35: =A34+1 -> 28 | B35: г. Братск Иркутской области | C35: Герметик ГОСТ Р 59522-2021 | D35: 440.02723.150200.1.6-КЖ5, лист 4 | F35: м3 | G35: 0.01
A36: =A35+1 -> 29 | B36: г. Братск Иркутской области | C36: Плиты пенополистирольные теплоизоляционные, тип Т, ППС15 | F36: м3 | G36: ='ВОР 150200 КЖ5'!D128 -> 0.43
A37: =A36+1 -> 30 | B37: г. Братск Иркутской области | C37: Шнур пенополиэтиленовый теплоизоляционный уплотнительный, сечение круглое сплошное, диаметр 30 мм | F37: м | G37: ='ВОР 150200 КЖ5'!D130 -> 18
A38: =A37+1 -> 31 | B38: г. Братск Иркутской области | C38: Праймер ПЛ-М | D38: ГОСТ 30693-2000 | F38: кг | G38: ='ВОР 150200 КЖ5'!D300 -> 121.15
A39: =A38+1 -> 32 | B39: г. Братск Иркутской области | C39: Мастика битумная изоляционная МБИ | D39: ГОСТ 30693-2000 | F39: кг | G39: ='ВОР 150200 КЖ5'!D302 -> 1211.5
A40: =A39+1 -> 33 | B40: г. Братск Иркутской области | C40: Состав клеевой двухкомпонентный инъекционный на основе эпоксидной смолы для восстановления арматурных выпусков и тяжелых анкерных креплений в бетоне, объем 330 мл | F40: шт. | G40: ='ВОР 150200 КЖ5'!D183+'ВОР 150200 КЖ5'!D196 -> 26
A41: ИТОГО:
A44: Составил: | D44: Менеджер группы по направлению "Общестроительные работы и генеральный план" | I44: Логинов А.А.
A47: Согласовано: | D47: Начальник ОМТС /коммерческой службы /коммерческий директор завода (подпись) ФИО
